azure/mgmt/containerorchestratorruntime/__init__.py
azure/mgmt/containerorchestratorruntime/_client.py
azure/mgmt/containerorchestratorruntime/_configuration.py
azure/mgmt/containerorchestratorruntime/_model_base.py
azure/mgmt/containerorchestratorruntime/_patch.py
azure/mgmt/containerorchestratorruntime/_serialization.py
azure/mgmt/containerorchestratorruntime/_validation.py
azure/mgmt/containerorchestratorruntime/_version.py
azure/mgmt/containerorchestratorruntime/py.typed
azure/mgmt/containerorchestratorruntime/aio/__init__.py
azure/mgmt/containerorchestratorruntime/aio/_client.py
azure/mgmt/containerorchestratorruntime/aio/_configuration.py
azure/mgmt/containerorchestratorruntime/aio/_patch.py
azure/mgmt/containerorchestratorruntime/aio/operations/__init__.py
azure/mgmt/containerorchestratorruntime/aio/operations/_operations.py
azure/mgmt/containerorchestratorruntime/aio/operations/_patch.py
azure/mgmt/containerorchestratorruntime/models/__init__.py
azure/mgmt/containerorchestratorruntime/models/_enums.py
azure/mgmt/containerorchestratorruntime/models/_models.py
azure/mgmt/containerorchestratorruntime/models/_patch.py
azure/mgmt/containerorchestratorruntime/operations/__init__.py
azure/mgmt/containerorchestratorruntime/operations/_operations.py
azure/mgmt/containerorchestratorruntime/operations/_patch.py
azure_mgmt_containerorchestratorruntime-1.0.0b1.dist-info/LICENSE
azure_mgmt_containerorchestratorruntime-1.0.0b1.dist-info/METADATA
azure_mgmt_containerorchestratorruntime-1.0.0b1.dist-info/WHEEL
azure_mgmt_containerorchestratorruntime-1.0.0b1.dist-info/top_level.txt
azure_mgmt_containerorchestratorruntime-1.0.0b1.dist-info/RECORD
